README.txt
analyzdat.py
setup.py
analyzdat.egg-info/PKG-INFO
analyzdat.egg-info/SOURCES.txt
analyzdat.egg-info/dependency_links.txt
analyzdat.egg-info/top_level.txt