Metadata-Version: 1.0
Name: analyzdat
Version: 1.1
Summary: There is "MNK", "beaut_plot", "partial_derivative", "random_error"
Home-page: UNKNOWN
Author: Your ggenchik
Author-email: feyke02@gmail.com
License: UNKNOWN
Platform: UNKNOWN
